racecar/__init__.py
racecar/_version.py
racecar/llh.py
racecar/sampler.py
racecar/version.py
racecar/algos/__init__.py
racecar/algos/algorithm.py
racecar/algos/badodab.py
racecar/algos/baoab.py
racecar/algos/hmc.py
racecar/algos/lm.py
racecar/algos/racecar.py
racecar/algos/rwmetropolis.py
racecar/algos/sghmc.py
racecar/algos/sgld.py
racecar-0.0.11.dist-info/LICENSE
racecar-0.0.11.dist-info/METADATA
racecar-0.0.11.dist-info/WHEEL
racecar-0.0.11.dist-info/top_level.txt
racecar-0.0.11.dist-info/RECORD
