Metadata-Version: 2.1
Name: racecar
Version: 0.0.11
Summary: A lightweight Bayesian sampling package
Home-page: https://github.com/c-matthews/racecar
Author: Charles Matthews
Author-email: mail@cmatthe.ws
License: UNKNOWN
Platform: UNKNOWN
Classifier: Programming Language :: Python :: 3
Classifier: License :: OSI Approved :: MIT License
Classifier: Operating System :: OS Independent
Requires-Python: >=3.6
Requires-Dist: numpy
Requires-Dist: scipy
